parameter_checks/__init__.py
parameter_checks/annotations.py
parameter_checks/hints.py
parameter_checks-1.0.0.dist-info/LICENSE
parameter_checks-1.0.0.dist-info/METADATA
parameter_checks-1.0.0.dist-info/WHEEL
parameter_checks-1.0.0.dist-info/top_level.txt
parameter_checks-1.0.0.dist-info/RECORD
