Metadata-Version: 2.1
Name: parameter-checks
Version: 1.0.0
Summary: Extend typehints to include dynamic checks (that might otherwise be dealt with by assertions) in Python.
Author: Sebastian Müller
Author-email: sebastian.nicolas.mueller@gmail.com
Project-URL: repository, https://github.com/snimu/parameter-checks
Project-URL: documentation, https://github.com/snimu/parameter-checks#readme
Keywords: parameters,return-values,checks,types,dynamic,decorator,typehint
Classifier: Programming Language :: Python
Classifier: Programming Language :: Python :: 3
Classifier: Programming Language :: Python :: 3.8
Classifier: Programming Language :: Python :: 3.9
Classifier: Programming Language :: Python :: 3.10
Classifier: Programming Language :: Python :: 3.11
Classifier: License :: OSI Approved :: MIT License
Classifier: Operating System :: OS Independent
Requires-Python: >=3.8
License-File: LICENSE
